<?xml version="1.0" encoding="UTF-8" standalone="yes"?>


<item>
<title>[COLOR=red][I][B]               EVENTOS[COLOR=white] ESPENCAT[/I][/B][/COLOR]</title>
<link>d</link>
<thumbnail>https://i.ibb.co/jfSg0vM/Darth-Vader.jpg</thumbnail>
<fanart>https://st.depositphotos.com/1005563/3256/i/450/depositphotos_32564723-stock-photo-sports-balls-a-lot-of.jpg</fanart>
</item>




<item> 
<title>[COLOR=yellow]                          FUTBOL              [/COLOR]</title>
<link>d</link>
<thumbnail>https://i.ibb.co/dbDR99f/Futbol.jpg</thumbnail>
<fanart>https://i.ibb.co/dbDR99f/Futbol.jpg</fanart>
</item>


<item>
<title>[COLOR=white]                        Valencia CF[/COLOR]</title>
<sportsdevil>https://g.dailysport.pw/x1/x1.m3u8</sportsdevil>
<User-Agent></User-Agent>
<referer></referer>
<info>En este apartado, el enlace que más me gusta para ver el Valencia</info>
<thumbnail>https://i.pinimg.com/originals/fa/18/69/fa1869e374038d502ed99ba647a3ec0a.jpg</thumbnail>
<fanart>https://upload.wikimedia.org/wikipedia/commons/thumb/0/03/CAMP_DE_MESTALLA_GRADA_DE_LA_MAR_2014.JPG/1200px-CAMP_DE_MESTALLA_GRADA_DE_LA_MAR_2014.JPG</fanart>
</item>

<item>
<title>[COLOR=cyan][COLOR red]xx:xx [COLOR white]---------------------[/COLOR][B]  ESP [/B][/COLOR]</title>
<sportsdevil>http://elixx.me/apsg.html</sportsdevil>
<User-Agent></User-Agent>
<referer></referer>
<thumbnail>https://i.ibb.co/dbDR99f/Futbol.jpg</thumbnail>
<fanart>https://i.ibb.co/dbDR99f/Futbol.jpg</fanart>
</item>

<item>
<title>[COLOR=cyan][COLOR red]xx:xx [COLOR white]---------------------[/COLOR][B]  ESP [/B][/COLOR]</title>
<sportsdevil>https://sportzonline.co/channels/hd/hd5.php</sportsdevil>
<User-Agent></User-Agent>
<referer></referer>
<thumbnail>https://i.ibb.co/dbDR99f/Futbol.jpg</thumbnail>
<fanart>https://i.ibb.co/dbDR99f/Futbol.jpg</fanart>
</item>


<item>
<title>[COLOR=cyan]─═☆☆═─   ٩(͡๏̯͡๏)۶  [COLOR red]20:45 [COLOR white]Valencia basket[/COLOR][B] [/B] [COLOR orange]PLEXUS[/COLOR]</title>
<link>plugin://program.plexus/?url=acestream://8cb69525386533f81c042f9e02d254f01b71d00c&amp;mode=1&amp;name=liveTV+Acestreams$$lsname=VH1 EUROPE </link>
<link>plugin://program.plexus/?url=acestream://ac17e755c7d9b3b1c7dac061d17a787d4051a14a&amp;mode=1&amp;name=liveTV+Acestreams$$lsname=Pruebas </link>
<link>plugin://program.plexus/?url=acestream://fd1bd57ab8a07464fa69cf56b6f906ad557ea38a&amp;mode=1&amp;name=liveTV+Acestreams$$lsname=Pruebas </link>
<thumbnail>https://i.imgur.com/7BBC3ec.png</thumbnail>
<fanart>https://i.pinimg.com/originals/8f/41/9b/8f419b52e2c1d2eba2f49c46b3a81385.jpg</fanart>
</item>


<item>
<title>[COLOR=white]FreeService 8W[/COLOR]</title>
<sportsdevil>https://ul.cdn946.net:8443/hls/p7mq6nc7v6i.m3u8?s=xW48LXapwh70FbGzkqxOAQ&e=1583114589</sportsdevil>
<User-Agent></User-Agent>
<referer></referer>
<thumbnail>https://i.ibb.co/dbDR99f/Futbol.jpg</thumbnail>
<fanart>https://i.ibb.co/dbDR99f/Futbol.jpg</fanart>
</item>

<item>
<title>[COLOR=white]FreeService 9W[/COLOR]</title>
<sportsdevil>https://ul.cdn946.net:8443/hls/9nncq7gl6aiw1v.m3u8?s=FqwzGfWjVcJtbvnXNJyfZw&e=1583114640</sportsdevil>
<User-Agent></User-Agent>
<referer></referer>
<info></info>
<thumbnail>https://i.ibb.co/dbDR99f/Futbol.jpg</thumbnail>
<fanart>https://i.ibb.co/dbDR99f/Futbol.jpg</fanart>
</item>

<item>
<title>[COLOR=white]FreeService 10W[/COLOR]</title>
<link>https://ul.cdn946.net:8443/hls/1ryhwzldt9oz099.m3u8?s=JkkfLsxf9V80vZMd5lcaYA&e=1583292792</link>
<User-Agent></User-Agent>
<referer></referer>
<info></info>
<thumbnail>https://i.ibb.co/dbDR99f/Futbol.jpg</thumbnail>
<fanart>https://i.ibb.co/dbDR99f/Futbol.jpg</fanart>
</item>

<item>
<title>[COLOR=white]Sportzonline HD6[/COLOR]</title>
<sportsdevil>https://sportzonline.to/channels/hd/hd6.php</sportsdevil>
<User-Agent></User-Agent>
<referer></referer>
<info>   --------------------- </info>
<thumbnail>https://i.ibb.co/dbDR99f/Futbol.jpg</thumbnail>
<fanart>https://i.ibb.co/dbDR99f/Futbol.jpg</fanart>
</item>

<item>
<title>[COLOR=white]Sportzonline HD6[/COLOR]</title>
<sportsdevil>https://ul.cdn946.net:8443/hls/55ught5e.m3u8?s=_Q7Gw6E2A1g1HlZ1XmVpWg&e=1583114786</sportsdevil>
<User-Agent></User-Agent>
<referer></referer>
<info>   --------------------- </info>
<thumbnail>https://i.ibb.co/dbDR99f/Futbol.jpg</thumbnail>
<fanart>https://i.ibb.co/dbDR99f/Futbol.jpg</fanart>
</item>




 

<item>
<title>[COLOR=yellow]                     BALONCESTO          [/COLOR]</title>
<link>d</link>
<thumbnail>https://i.ibb.co/Wc2nyh3/Basket.jpg</thumbnail>
<fanart>https://i.ibb.co/Wc2nyh3/Basket.jpg</fanart>
</item>


<item>
<title>[COLOR=white]*****[/COLOR]</title>
<sportsdevil>https://dailysport.pw/c5.php</sportsdevil>
<User-Agent></User-Agent>
<referer></referer>
<thumbnail>https://i.ibb.co/Wc2nyh3/Basket.jpg</thumbnail>
<fanart>https://i.ibb.co/Wc2nyh3/Basket.jpg</fanart>
</item>

<item> 
<title>[COLOR=yellow]                         MOTO GP              [/COLOR]</title>
<link>d</link>
<thumbnail>https://i.pinimg.com/originals/1a/da/44/1ada442c5d5e97a72c0ebdf0243fdeea.jpg</thumbnail>
<fanart>https://e00-marca.uecdn.es/assets/multimedia/imagenes/2018/07/10/15312313057382.jpg</fanart>
</item>

<item>
<title>[COLOR=white]*****[/COLOR]</title>
<sportsdevil>https://dailysport.pw/c5.php</sportsdevil>
<User-Agent></User-Agent>
<referer></referer>
<thumbnail>https://e00-marca.uecdn.es/assets/multimedia/imagenes/2019/02/27/15512702734576.jpg</thumbnail>
<fanart>https://e00-marca.uecdn.es/assets/multimedia/imagenes/2018/07/10/15312313057382.jpg</fanart>
</item>

